  
{
    "name": "MainNet",
    "pollTime": "5000",
    "sites": [
      {
        "protocol": "https",
        "url": "test1.cityofzion.io",
        "port": "443"
      },
      {
        "protocol": "https",
        "url": "test2.cityofzion.io",
        "port": "443"
      },
      {
        "protocol": "https",
        "url": "test3.cityofzion.io",
        "port": "443"
      },
      {
        "protocol": "http",
        "url": "seed1.ngd.network",
        "port": "20332"
      },
      {
        "protocol": "http",
        "url": "seed2.ngd.network",
        "port": "20332"
      },
      {
        "protocol": "http",
        "url": "seed3.ngd.network",
        "port": "20332"
      },
      {
        "protocol": "http",
        "url": "seed4.ngd.network",
        "port": "20332"
      },
      {
        "protocol": "http",
        "url": "seed5.ngd.network",
        "port": "20332"
      },
      {
        "protocol": "http",
        "url": "seed6.ngd.network",
        "port": "20332"
      },
      {
        "protocol": "http",
        "url": "seed7.ngd.network",
        "port": "20332"
      },
      {
        "protocol": "http",
        "url": "seed8.ngd.network",
        "port": "20332"
      },
      {
        "protocol": "http",
        "url": "seed9.ngd.network",
        "port": "20332"
      },
      {
        "protocol": "http",
        "url": "seed10.ngd.network",
        "port": "20332"
      }
    ]
  }